{
  "name": "ReportResults",
  "namespace": "Reports",
  "accessModifier": "global",
  "definitionModifier": "",
  "withSharing": false,
  "inheritedSharing": false,
  "isEnum": false,
  "enumValues": [],
  "extendsType": "",
  "isInterface": false,
  "implements": [],
  "classes": {},
  "enums": {},
  "fields": [],
  "constructors": [],
  "methods": [
    {
      "name": "getAllData",
      "signature": "",
      "description": "Returns all report data.",
      "params": [],
      "datatype": "Boolean"
    },
    {
      "name": "getFactMap",
      "signature": "",
      "description": "Returns summary-level data or summary and detailed data for each row or column grouping. Detailed data is available if the includeDetails parameter is set to true when the report is run.",
      "params": [],
      "datatype": "Map<String,Reports.ReportFact>"
    },
    {
      "name": "getGroupingsAcross",
      "signature": "",
      "description": "Returns a collection of column groupings, keys, and values.",
      "params": [],
      "datatype": "Reports.Dimension"
    },
    {
      "name": "getGroupingsDown",
      "signature": "",
      "description": "Returns a collection of row groupings, keys, and values.",
      "params": [],
      "datatype": "Reports.Dimension"
    },
    {
      "name": "getHasDetailRows",
      "signature": "",
      "description": "Returns information about whether the fact map has detail rows.",
      "params": [],
      "datatype": "Boolean"
    },
    {
      "name": "getReportExtendedMetadata",
      "signature": "",
      "description": "Returns additional, detailed metadata about the report, including data type and label information for groupings and summaries.",
      "params": [],
      "datatype": "Reports.ReportExtendedMetadata"
    },
    {
      "name": "getReportMetadata",
      "signature": "",
      "description": "Returns metadata about the report, including grouping and summary information.",
      "params": [],
      "datatype": "Reports.ReportMetadata"
    }
  ],
  "description": "Contains the results of running a report.",
  "docLink": "https://developer.salesforce.com/docs/atlas.en-us.apexcode.meta/apexcode/apex_class_reports_reportresults.htm"
}