{
  "name": "MilestoneTriggerTimeCalculator",
  "namespace": "Support",
  "accessModifier": "global",
  "definitionModifier": "",
  "withSharing": false,
  "inheritedSharing": false,
  "isEnum": false,
  "enumValues": [],
  "extendsType": "",
  "isInterface": true,
  "implements": [],
  "classes": {},
  "enums": {},
  "fields": [],
  "constuctors": [],
  "methods": [
    {
      "name": "calculateMilestoneTriggerTime",
      "signature": "",
      "description": "Calculates the milestone trigger time based on the specified case and milestone type and returns the time in minutes.",
      "methodParams": [
        {
          "name": "caseId",
          "datatype": "String"
        },
        {
          "name": "milestoneTypeId",
          "datatype": "String"
        }
      ],
      "datatype": "Integer"
    }
  ],
  "description": "The Support.MilestoneTriggerTimeCalculator interface calculates the time trigger for a milestone.",
  "docLink": "https://developer.salesforce.com/docs/atlas.en-us.apexcode.meta/apexcode/apex_interface_support_milestonetriggertimecalculator.htm#apex_interface_support_milestonetriggertimecalculator"
}